[{"word": "overmark", "similarity": 0.8001487615886264}, {"word": "undermark", "similarity": 0.8001487615886264}, {"word": "mark", "similarity": 0.7506825122823415}, {"word": "markest", "similarity": 0.7274308092927628}, {"word": "marketh", "similarity": 0.7274308092927628}, {"word": "markless", "similarity": 0.6995972753081345}, {"word": "marking", "similarity": 0.6939131398710258}, {"word": "mismark", "similarity": 0.6908782070596268}, {"word": "premarked", "similarity": 0.6650670763753186}, {"word": "mismarking", "similarity": 0.664734755433213}, {"word": "unmarkable", "similarity": 0.6644313524861327}, {"word": "markable", "similarity": 0.6526477360957497}, {"word": "bemark", "similarity": 0.6460280659115}, {"word": "kinemerk", "similarity": 0.6396027457796684}, {"word": "bespot", "similarity": 0.6271038225410872}, {"word": "outmark", "similarity": 0.6269149093583}, {"word": "marked", "similarity": 0.6062903125237591}, {"word": "bimaculate", "similarity": 0.5997030552345188}, {"word": "unmark", "similarity": 0.5967492613338609}, {"word": "markworthy", "similarity": 0.5730065610541947}, {"word": "signation", "similarity": 0.5675203808833699}, {"word": "markie", "similarity": 0.5526901389466624}, {"word": "dignotion", "similarity": 0.5460005726275501}, {"word": "caract", "similarity": 0.5451667994152646}, {"word": "scratchmark", "similarity": 0.5411425340901841}, {"word": "denotable", "similarity": 0.5401565612231314}, {"word": "bestain", "similarity": 0.5267395524610051}, {"word": "pressmark", "similarity": 0.5228318986285694}, {"word": "lugmark", "similarity": 0.5212146603685758}, {"word": "thumbmark", "similarity": 0.5168239533509814}, {"word": "thumbmarked", "similarity": 0.5128046770125612}, {"word": "bepenciled", "similarity": 0.5093473708575309}, {"word": "markka", "similarity": 0.5033770479977755}, {"word": "enstamp", "similarity": 0.5004019918084505}, {"word": "instamp", "similarity": 0.49841472803628467}, {"word": "logomark", "similarity": 0.4983772404013055}, {"word": "markings", "similarity": 0.4963111264918605}, {"word": "punctator", "similarity": 0.4928667111433683}, {"word": "catchmark", "similarity": 0.48836951713191107}, {"word": "insignment", "similarity": 0.48586621733732993}, {"word": "marcus", "similarity": 0.4850083790025236}, {"word": "swanmark", "similarity": 0.4814850017037277}, {"word": "servicemark", "similarity": 0.47702126846460885}, {"word": "brandmark", "similarity": 0.473940041631897}, {"word": "marksheet", "similarity": 0.4734530324132313}, {"word": "deutschmark", "similarity": 0.4726341670665375}, {"word": "aftersign", "similarity": 0.46930886551195244}, {"word": "markman", "similarity": 0.46833191288879605}, {"word": "matchmark", "similarity": 0.4673676946013971}, {"word": "lapmark", "similarity": 0.4649336691035759}, {"word": "stampability", "similarity": 0.46344625692577274}, {"word": "markan", "similarity": 0.46069493162804975}, {"word": "fretten", "similarity": 0.458132683456649}, {"word": "cutmark", "similarity": 0.45778164154714573}, {"word": "atmark", "similarity": 0.4539091639254146}, {"word": "undenotable", "similarity": 0.45038863536218654}, {"word": "signate", "similarity": 0.4501237668618027}, {"word": "obelism", "similarity": 0.44774603164615834}, {"word": "bitemark", "similarity": 0.44636644972872547}, {"word": "charactery", "similarity": 0.44578473427318027}, {"word": "dermatograph", "similarity": 0.44413737918029494}, {"word": "diple", "similarity": 0.43934948208973684}, {"word": "trademarks", "similarity": 0.4383879231131304}, {"word": "platemark", "similarity": 0.4367658630854429}, {"word": "punctation", "similarity": 0.43604508522470137}, {"word": "superindex", "similarity": 0.43320144198348337}, {"word": "trademark", "similarity": 0.42605400738150495}, {"word": "marker", "similarity": 0.42579071608324354}, {"word": "assprint", "similarity": 0.423447260486459}, {"word": "buttprint", "similarity": 0.4230656657736439}, {"word": "surmark", "similarity": 0.42288135323556403}, {"word": "lineated", "similarity": 0.420957211491067}, {"word": "ostmark", "similarity": 0.4205467092031906}, {"word": "hallmarks", "similarity": 0.4201209021203144}, {"word": "finmark", "similarity": 0.41970241101671957}, {"word": "strandline", "similarity": 0.41722901124302497}, {"word": "idiograph", "similarity": 0.41600743656777595}, {"word": "brushmark", "similarity": 0.4154518842090445}, {"word": "hallmark", "similarity": 0.4138261667577728}, {"word": "marque", "similarity": 0.40547611505112807}, {"word": "tilka", "similarity": 0.4041425956437767}, {"word": "punctuation", "similarity": 0.4016690185034275}, {"word": "noonmark", "similarity": 0.40064642825789193}, {"word": "interpunction", "similarity": 0.39994613309281246}, {"word": "becross", "similarity": 0.39899443236933907}, {"word": "placemark", "similarity": 0.3979664283372415}, {"word": "toothmark", "similarity": 0.3972293435932916}, {"word": "asterisked", "similarity": 0.3969851742057951}, {"word": "splotchy", "similarity": 0.39573525599808623}, {"word": "countermark", "similarity": 0.39454887969249186}, {"word": "prononc\u00e9", "similarity": 0.3923341693523317}, {"word": "denotement", "similarity": 0.3913598006205417}, {"word": "scarred", "similarity": 0.38997766763607117}, {"word": "markers", "similarity": 0.387386872171217}, {"word": "bipunctate", "similarity": 0.38697407133722134}, {"word": "hallmarking", "similarity": 0.3853505941382986}, {"word": "denotate", "similarity": 0.38406415078238687}, {"word": "marx", "similarity": 0.3834204188969193}, {"word": "bestreak", "similarity": 0.38339636317758236}, {"word": "counterstamp", "similarity": 0.3831338625849519}, {"word": "toothmarks", "similarity": 0.3823278332214629}, {"word": "mispunctuation", "similarity": 0.3822704248018072}, {"word": "microstamp", "similarity": 0.38081489954375414}, {"word": "repunctuation", "similarity": 0.379799855802251}, {"word": "floodmark", "similarity": 0.37832810821799573}, {"word": "hallmarked", "similarity": 0.37773637410124816}, {"word": "markes", "similarity": 0.37766904059516737}, {"word": "splatch", "similarity": 0.3744924213112556}, {"word": "denoted", "similarity": 0.37351426573681235}, {"word": "mintmark", "similarity": 0.3733006047136403}, {"word": "punctuations", "similarity": 0.37101354265672554}, {"word": "punctuate", "similarity": 0.37090624287991586}, {"word": "stigme", "similarity": 0.3697801011048699}, {"word": "dateaversary", "similarity": 0.3690807651352598}, {"word": "repunctuate", "similarity": 0.3688692997534245}, {"word": "catface", "similarity": 0.3682021586595595}, {"word": "mottling", "similarity": 0.3681829621520476}, {"word": "headmark", "similarity": 0.3669573278201921}, {"word": "pencilling", "similarity": 0.3664729529927937}, {"word": "nonsignifying", "similarity": 0.36644126537004296}, {"word": "rescore", "similarity": 0.36598832011794025}, {"word": "reichsmark", "similarity": 0.36457476582533593}, {"word": "denote", "similarity": 0.3645462137756072}, {"word": "scars", "similarity": 0.3639198776492515}, {"word": "branding", "similarity": 0.36343475834168276}, {"word": "milestone", "similarity": 0.36237698889062536}, {"word": "dotting", "similarity": 0.3621571227114431}, {"word": "mispunctuate", "similarity": 0.362038896582416}, {"word": "denotator", "similarity": 0.3606606632555329}, {"word": "denoting", "similarity": 0.36050239652850946}, {"word": "interpunctuation", "similarity": 0.36031761343573304}, {"word": "quatercentennial", "similarity": 0.35972132898256065}, {"word": "anniversary", "similarity": 0.35943985805297}, {"word": "quatercentenary", "similarity": 0.3590454741245406}, {"word": "teethmarks", "similarity": 0.35889661051844257}, {"word": "indicia", "similarity": 0.3583119110989688}, {"word": "quadringenary", "similarity": 0.3582284340675151}, {"word": "inkdot", "similarity": 0.3582181131547705}, {"word": "anniversaries", "similarity": 0.35711940658839686}, {"word": "mispoint", "similarity": 0.35693140478357194}, {"word": "diacritical", "similarity": 0.3567178669436641}, {"word": "stigmatically", "similarity": 0.3559996751133552}, {"word": "catscratch", "similarity": 0.3555310574165669}, {"word": "hypodiastole", "similarity": 0.35517294254591125}, {"word": "tiver", "similarity": 0.3548777082454704}, {"word": "denotee", "similarity": 0.35395863837809227}, {"word": "signifyingly", "similarity": 0.3538124531890929}, {"word": "inburn", "similarity": 0.3531198760745973}, {"word": "birthmarks", "similarity": 0.3529989919314048}, {"word": "indelibly", "similarity": 0.3520520661838875}, {"word": "blotches", "similarity": 0.35180330112324887}, {"word": "signify", "similarity": 0.3514860647861533}, {"word": "pockmarks", "similarity": 0.3513614102281501}, {"word": "denoteth", "similarity": 0.3513187914065639}, {"word": "signifying", "similarity": 0.35129437335725383}, {"word": "landmark", "similarity": 0.3509635661706864}, {"word": "micropunctate", "similarity": 0.3502767125559176}, {"word": "foxing", "similarity": 0.3499562183130997}, {"word": "brand", "similarity": 0.3490640451511953}, {"word": "earprint", "similarity": 0.3484247663406157}, {"word": "milestones", "similarity": 0.3470333418815582}, {"word": "unsignifiable", "similarity": 0.34689528673339187}, {"word": "punctuated", "similarity": 0.34684609236885877}, {"word": "registrability", "similarity": 0.3467248637468372}, {"word": "obelized", "similarity": 0.346357615007785}, {"word": "punctate", "similarity": 0.34628924681301243}, {"word": "waymark", "similarity": 0.3461485071396493}, {"word": "waymarker", "similarity": 0.3458803648084579}, {"word": "hoofmark", "similarity": 0.34585161337242565}, {"word": "octocentenary", "similarity": 0.34469614025731105}, {"word": "moustachial", "similarity": 0.3434609284630629}, {"word": "suggilation", "similarity": 0.3431671337150518}, {"word": "maculated", "similarity": 0.3424724208047055}, {"word": "multipunctate", "similarity": 0.3409542358077411}, {"word": "indelible", "similarity": 0.3404879362511757}, {"word": "punctuator", "similarity": 0.3391109098040653}, {"word": "genericide", "similarity": 0.33848312726097785}, {"word": "osteomarker", "similarity": 0.33842158668027345}, {"word": "quincentennial", "similarity": 0.33836199695783853}, {"word": "dots", "similarity": 0.33765903798651953}, {"word": "impunctate", "similarity": 0.33728899050995315}, {"word": "quadringentenary", "similarity": 0.3369053479258137}, {"word": "meetaversary", "similarity": 0.3367296560381079}, {"word": "unpunctuate", "similarity": 0.3364987928591954}, {"word": "dotted", "similarity": 0.33609311936539343}, {"word": "te\u010dka", "similarity": 0.3360132262917667}, {"word": "landmarks", "similarity": 0.33506367042318186}, {"word": "multimarker", "similarity": 0.33485533366728065}, {"word": "indelibility", "similarity": 0.33413978794081095}, {"word": "diacritic", "similarity": 0.3317323272981292}, {"word": "signified", "similarity": 0.33109828310360534}, {"word": "deboss", "similarity": 0.33104351827654355}, {"word": "quincentenary", "similarity": 0.33039299606082845}, {"word": "punctuational", "similarity": 0.3296911752869976}, {"word": "symbols", "similarity": 0.32931173248168083}, {"word": "neuromarker", "similarity": 0.328922949443713}, {"word": "unregistrable", "similarity": 0.3283922584461211}, {"word": "distinguishing", "similarity": 0.32821879012469357}, {"word": "unregistrability", "similarity": 0.3273903010004076}, {"word": "noteworthiness", "similarity": 0.3273552403237294}, {"word": "indicate", "similarity": 0.3269814457395035}, {"word": "indicatory", "similarity": 0.3269548595043486}, {"word": "bimillenary", "similarity": 0.326625431396654}, {"word": "indigitate", "similarity": 0.3265461034376977}, {"word": "interpunct", "similarity": 0.32594731245292796}, {"word": "overscore", "similarity": 0.32488118375945835}, {"word": "bethumb", "similarity": 0.32442472888803403}, {"word": "milliary", "similarity": 0.3243632811438884}, {"word": "underdot", "similarity": 0.3240723841497684}, {"word": "consignify", "similarity": 0.32399913686075454}, {"word": "jhandi", "similarity": 0.32289150948043976}, {"word": "blotch", "similarity": 0.3228906130569547}, {"word": "bimillenial", "similarity": 0.32284636591471605}, {"word": "decaversary", "similarity": 0.32264656714849527}, {"word": "overdot", "similarity": 0.3225214296814499}, {"word": "microbrand", "similarity": 0.32248720039053597}, {"word": "signs", "similarity": 0.32210613753829737}, {"word": "indistinctive", "similarity": 0.32195616128565596}, {"word": "indicium", "similarity": 0.3215204190776731}, {"word": "dot", "similarity": 0.32099744922097495}, {"word": "speckling", "similarity": 0.3204034317920649}, {"word": "inkstain", "similarity": 0.3202985392217596}, {"word": "merestone", "similarity": 0.319971057433551}, {"word": "indicial", "similarity": 0.31975979565298945}, {"word": "crayola", "similarity": 0.319466182337394}, {"word": "nebulated", "similarity": 0.318863256937167}, {"word": "signalize", "similarity": 0.31864960552586097}, {"word": "hoofprint", "similarity": 0.3182683472215151}, {"word": "unregisterable", "similarity": 0.31806806323052683}, {"word": "septicentennial", "similarity": 0.31755146453837896}, {"word": "punctated", "similarity": 0.31740465888060726}, {"word": "indicatable", "similarity": 0.31739578152959946}, {"word": "insignias", "similarity": 0.3171235971109559}, {"word": "signifies", "similarity": 0.3170859414445245}, {"word": "quasquicentennial", "similarity": 0.31677375831543103}, {"word": "bimillennial", "similarity": 0.31630232990026985}, {"word": "subsign", "similarity": 0.3162393102474799}, {"word": "smark", "similarity": 0.31612720086280444}, {"word": "commemorates", "similarity": 0.31599001751631534}, {"word": "indentations", "similarity": 0.31574136557556615}, {"word": "traces", "similarity": 0.31555884865961736}, {"word": "label", "similarity": 0.31555481308641126}, {"word": "marky", "similarity": 0.31552706495980176}, {"word": "subbrand", "similarity": 0.31551126457916084}, {"word": "maculose", "similarity": 0.3153827902168754}, {"word": "phylomarker", "similarity": 0.31512195198322596}, {"word": "indicating", "similarity": 0.3150105536937747}, {"word": "signum", "similarity": 0.31489068196353087}, {"word": "notched", "similarity": 0.31443968426990615}, {"word": "monumented", "similarity": 0.31436463161516776}, {"word": "counterindicate", "similarity": 0.31391076295071024}, {"word": "indicatest", "similarity": 0.31391076295071024}, {"word": "indicateth", "similarity": 0.31391076295071024}, {"word": "sharpie", "similarity": 0.3136079904970964}, {"word": "branded", "similarity": 0.3132763261683569}, {"word": "marginalia", "similarity": 0.3129984554672608}, {"word": "labels", "similarity": 0.31292338208270976}, {"word": "becolour", "similarity": 0.3126681196840785}, {"word": "scar", "similarity": 0.3126128427169441}, {"word": "marxology", "similarity": 0.31260091300866394}, {"word": "commemorated", "similarity": 0.31258690195005334}, {"word": "pock", "similarity": 0.3124123783846222}, {"word": "ecphoneme", "similarity": 0.3120366662743848}, {"word": "stamp", "similarity": 0.312029694021714}, {"word": "pockmark", "similarity": 0.31149943620056003}, {"word": "initials", "similarity": 0.3111496150232226}, {"word": "smudges", "similarity": 0.31083737462259525}, {"word": "seromarker", "similarity": 0.3107068978352891}, {"word": "brisure", "similarity": 0.31065523573665405}, {"word": "stains", "similarity": 0.3101814040232969}, {"word": "underscorer", "similarity": 0.31011732883536386}, {"word": "denotes", "similarity": 0.3099317926224986}, {"word": "nonscarring", "similarity": 0.3096099804942754}, {"word": "virgule", "similarity": 0.30938376541173546}, {"word": "smudge", "similarity": 0.3092647351496902}, {"word": "marxological", "similarity": 0.3089906970604931}, {"word": "hebdomadiversary", "similarity": 0.30896870734839826}, {"word": "intoningly", "similarity": 0.3085516614885278}, {"word": "bicentenary", "similarity": 0.30797805259196864}, {"word": "subindicate", "similarity": 0.30784866831711516}, {"word": "mk", "similarity": 0.30749141267913915}, {"word": "distinction", "similarity": 0.30730017322508574}, {"word": "resignify", "similarity": 0.3068659504454717}, {"word": "marco", "similarity": 0.30674983621127755}, {"word": "supersign", "similarity": 0.3065874023007495}, {"word": "pugmark", "similarity": 0.3065680828206316}, {"word": "scarring", "similarity": 0.3061736250983576}, {"word": "teethmark", "similarity": 0.3061158888226414}, {"word": "obsignate", "similarity": 0.30589742145520316}, {"word": "signalise", "similarity": 0.3055979073169066}, {"word": "punctulate", "similarity": 0.30526872107818653}, {"word": "fingermarks", "similarity": 0.305140485200136}, {"word": "celebrates", "similarity": 0.30511220462897815}, {"word": "pocks", "similarity": 0.3051107448369337}, {"word": "inked", "similarity": 0.30425056522073485}, {"word": "demark", "similarity": 0.3041678654415644}, {"word": "foralite", "similarity": 0.3041188205537015}, {"word": "inclamation", "similarity": 0.3039541415314791}, {"word": "indical", "similarity": 0.30395026889618343}, {"word": "forepoint", "similarity": 0.3039218267798258}, {"word": "denotatum", "similarity": 0.30391515707399774}, {"word": "electrographic", "similarity": 0.3037967152767565}, {"word": "semilandmark", "similarity": 0.3036054381376387}, {"word": "distinguo", "similarity": 0.3034872665720617}, {"word": "unmarked", "similarity": 0.30303662568420475}, {"word": "pockmarked", "similarity": 0.30287119577516974}, {"word": "unpunctuated", "similarity": 0.3026177557043642}, {"word": "tricesimation", "similarity": 0.3025808154013258}, {"word": "pocked", "similarity": 0.3024145553638253}, {"word": "points", "similarity": 0.30223776325635476}, {"word": "unasterisked", "similarity": 0.30219777105102236}, {"word": "prickpunch", "similarity": 0.3020972078226742}, {"word": "marcatissimo", "similarity": 0.3019845569158305}, {"word": "blotchily", "similarity": 0.3014075912890031}, {"word": "plurisignify", "similarity": 0.301393012361159}, {"word": "staurogram", "similarity": 0.30133668957113163}, {"word": "megabrand", "similarity": 0.3012980717575626}, {"word": "brandest", "similarity": 0.30113218341631537}, {"word": "brandeth", "similarity": 0.30113218341631537}, {"word": "misstamp", "similarity": 0.3009470922192843}, {"word": "overstamp", "similarity": 0.3009470922192843}, {"word": "stampest", "similarity": 0.3009470922192843}, {"word": "stampeth", "similarity": 0.3009470922192843}, {"word": "handmark", "similarity": 0.3005312656878276}, {"word": "tagged", "similarity": 0.30035080782093737}, {"word": "striae", "similarity": 0.3002163824719114}, {"word": "inkproof", "similarity": 0.29988175724961386}, {"word": "celebrated", "similarity": 0.2998189708351136}, {"word": "cropmark", "similarity": 0.2996548533278875}, {"word": "superbrand", "similarity": 0.2996215191362264}, {"word": "labelable", "similarity": 0.29952978646183015}, {"word": "milepost", "similarity": 0.2993175829420808}, {"word": "spots", "similarity": 0.29902417538479814}, {"word": "maculation", "similarity": 0.2988369411901578}, {"word": "restamp", "similarity": 0.29850532132769414}, {"word": "signposts", "similarity": 0.2984007076562097}, {"word": "chinagraph", "similarity": 0.29779649300498817}, {"word": "unblotched", "similarity": 0.29767548617512757}, {"word": "insignia", "similarity": 0.29696690496075173}, {"word": "registrable", "similarity": 0.296717722621444}, {"word": "fingermark", "similarity": 0.29649640255790327}, {"word": "distinctions", "similarity": 0.29633727818923916}, {"word": "marques", "similarity": 0.2963037623190643}, {"word": "rubricate", "similarity": 0.2962822255072198}, {"word": "decigrade", "similarity": 0.2962728010700947}, {"word": "technosignature", "similarity": 0.2960531475643473}, {"word": "besmudge", "similarity": 0.2960062577755958}, {"word": "handprints", "similarity": 0.29592562588496946}, {"word": "stamped", "similarity": 0.29582924722494325}, {"word": "semicentennial", "similarity": 0.29570630536294634}, {"word": "indication", "similarity": 0.2948893767638094}, {"word": "marxologist", "similarity": 0.294405208496919}, {"word": "macule", "similarity": 0.2942552459199077}, {"word": "fissidentate", "similarity": 0.29408428072727805}, {"word": "distinctiveness", "similarity": 0.2938173776114138}, {"word": "sign", "similarity": 0.2937162928829792}, {"word": "cicatrice", "similarity": 0.2935279092009691}, {"word": "stampable", "similarity": 0.29336376673985637}, {"word": "signaturist", "similarity": 0.2931649599651475}, {"word": "exclamation", "similarity": 0.29293639265929106}, {"word": "gravemarker", "similarity": 0.29284100460917145}, {"word": "conspicuous", "similarity": 0.2926169318863443}, {"word": "foreheads", "similarity": 0.29251588051843413}, {"word": "centenary", "similarity": 0.29250505835467416}, {"word": "imprints", "similarity": 0.29148826475015616}, {"word": "commemorable", "similarity": 0.29138588593106046}, {"word": "commemorator", "similarity": 0.29138588593106046}, {"word": "scuffing", "similarity": 0.2913688721685932}, {"word": "notory", "similarity": 0.29112932839196154}, {"word": "commemorate", "similarity": 0.2910653191705416}, {"word": "registerable", "similarity": 0.29102773986269564}, {"word": "signalizes", "similarity": 0.29101603712235713}, {"word": "chalked", "similarity": 0.29096196274475106}, {"word": "blemishes", "similarity": 0.2907830149036976}, {"word": "trimillennial", "similarity": 0.29074513573439387}, {"word": "kitemark", "similarity": 0.2903948246969892}, {"word": "commemorating", "similarity": 0.2902764020681315}, {"word": "antibranding", "similarity": 0.2901145617413051}, {"word": "indicates", "similarity": 0.289614707403108}, {"word": "lambel", "similarity": 0.2895879894312196}, {"word": "ineffaceably", "similarity": 0.2894548312254307}, {"word": "emaculation", "similarity": 0.2888023953820091}, {"word": "branson", "similarity": 0.2886966986963326}, {"word": "unerasable", "similarity": 0.2886911862705237}, {"word": "stigmata", "similarity": 0.28857820530034}, {"word": "signifier", "similarity": 0.2884574594324836}, {"word": "distinctive", "similarity": 0.28826409355713556}, {"word": "undistinctive", "similarity": 0.2882162520393949}, {"word": "quadricentennial", "similarity": 0.2877716368602642}, {"word": "birthmark", "similarity": 0.28729307058020276}, {"word": "spencers", "similarity": 0.28724319284131183}, {"word": "blotched", "similarity": 0.2869654504971592}, {"word": "blotchy", "similarity": 0.2868932626736495}, {"word": "twainish", "similarity": 0.28678982918120194}, {"word": "bimillennium", "similarity": 0.28667318901086664}, {"word": "nonregistrable", "similarity": 0.2865912750529628}, {"word": "blotchwork", "similarity": 0.28649430242496254}, {"word": "moniment", "similarity": 0.2864420471190393}, {"word": "notations", "similarity": 0.286048787534927}, {"word": "photolabel", "similarity": 0.2857534793381482}, {"word": "eroteme", "similarity": 0.28552704629122727}, {"word": "symbol", "similarity": 0.2854666097020324}, {"word": "striations", "similarity": 0.28543412759426523}, {"word": "tercentenary", "similarity": 0.2853818433747658}, {"word": "imprint", "similarity": 0.28501084549864875}, {"word": "bicharacteristic", "similarity": 0.2846731812239411}, {"word": "notation", "similarity": 0.2846515070537106}, {"word": "foresignify", "similarity": 0.2845392339652031}, {"word": "emblazoning", "similarity": 0.28439909683767434}, {"word": "bicentennial", "similarity": 0.28419612862987764}, {"word": "sesquicentenary", "similarity": 0.28416525688411504}, {"word": "significate", "similarity": 0.28382751056087857}, {"word": "ticks", "similarity": 0.2837809820776998}, {"word": "tickable", "similarity": 0.28376975199949805}, {"word": "unmarkedness", "similarity": 0.2834748658856226}, {"word": "badges", "similarity": 0.28344378269160553}, {"word": "plurisignifying", "similarity": 0.283414915073172}, {"word": "jubilarian", "similarity": 0.28327896843621014}, {"word": "subvisible", "similarity": 0.28321341285308266}, {"word": "visible", "similarity": 0.2829675431115458}, {"word": "prestamped", "similarity": 0.28245359983606805}, {"word": "uloid", "similarity": 0.28223716965444806}, {"word": "marc", "similarity": 0.281985780082195}, {"word": "paraph", "similarity": 0.2819552101972101}, {"word": "overbrand", "similarity": 0.2819388502622941}, {"word": "hypervisible", "similarity": 0.28178062337696896}, {"word": "dotplot", "similarity": 0.2817173148372595}, {"word": "tenth", "similarity": 0.28163060237782156}, {"word": "checkmark", "similarity": 0.2814081175053042}, {"word": "distinctor", "similarity": 0.2810780674755849}, {"word": "cuspidal", "similarity": 0.280840147896242}, {"word": "coincides", "similarity": 0.2807073770592529}, {"word": "celebratable", "similarity": 0.28052516787680937}, {"word": "badge", "similarity": 0.2802827083438797}, {"word": "markin", "similarity": 0.28023725593144394}, {"word": "trademarked", "similarity": 0.28011777968520185}, {"word": "smudged", "similarity": 0.2799604649117195}, {"word": "brands", "similarity": 0.2797718580295027}, {"word": "pfennig", "similarity": 0.2796009790017179}, {"word": "maculate", "similarity": 0.2794939659998668}, {"word": "celebrate", "similarity": 0.27949388377475737}, {"word": "labelless", "similarity": 0.27935036536092145}, {"word": "commaless", "similarity": 0.2792299324215802}, {"word": "marcia", "similarity": 0.2790874262085132}, {"word": "footmark", "similarity": 0.27906800149531785}, {"word": "setmark", "similarity": 0.2789748528385753}, {"word": "##th", "similarity": 0.2789299454089307}, {"word": "misdistinguish", "similarity": 0.278776281883052}, {"word": "multibranded", "similarity": 0.2787456533739467}, {"word": "scoreth", "similarity": 0.27794123465091164}, {"word": "ecphonesis", "similarity": 0.27748538565568365}, {"word": "kneeprint", "similarity": 0.27744837430608665}, {"word": "antismudge", "similarity": 0.2772306577337366}, {"word": "nonresidue", "similarity": 0.27715309215533546}, {"word": "punctiform", "similarity": 0.2771445788665667}, {"word": "cicatrix", "similarity": 0.27711124666403786}, {"word": "multibranding", "similarity": 0.27703212014056655}, {"word": "underline", "similarity": 0.27696280258741685}, {"word": "examinations", "similarity": 0.2769620227700334}, {"word": "point", "similarity": 0.276669836319668}, {"word": "notabilia", "similarity": 0.27657473416940126}, {"word": "phanero", "similarity": 0.2765502604428454}, {"word": "immunomarker", "similarity": 0.27624494732391625}, {"word": "sixtieth", "similarity": 0.276036421528809}, {"word": "twentieth", "similarity": 0.27568885690351025}, {"word": "fiftieth", "similarity": 0.27528855443421907}, {"word": "denotive", "similarity": 0.2748490909200064}, {"word": "nuqta", "similarity": 0.27465306396378053}, {"word": "blemish", "similarity": 0.2741313493454183}, {"word": "underlining", "similarity": 0.27409613325938953}, {"word": "fingerpost", "similarity": 0.27401865621657534}, {"word": "splotches", "similarity": 0.2740077404653574}, {"word": "logotypy", "similarity": 0.273923318914019}, {"word": "freckles", "similarity": 0.27385277545898906}, {"word": "coinciding", "similarity": 0.2738260129624249}, {"word": "obsign", "similarity": 0.2736325748151637}, {"word": "incised", "similarity": 0.2734812503403861}, {"word": "pfennigs", "similarity": 0.2734567716028463}, {"word": "pocking", "similarity": 0.27326682892234444}, {"word": "monthiversary", "similarity": 0.2731799160448536}, {"word": "marring", "similarity": 0.2731482157927861}, {"word": "indented", "similarity": 0.2729164790500933}, {"word": "resmudge", "similarity": 0.27284488986725924}, {"word": "handprint", "similarity": 0.2727847561925312}, {"word": "foresign", "similarity": 0.27278184047302106}, {"word": "markedness", "similarity": 0.2724856345411081}, {"word": "underlines", "similarity": 0.2724093337476935}, {"word": "noticeable", "similarity": 0.2723833459103402}, {"word": "datestamp", "similarity": 0.27235333391471267}, {"word": "hypograph", "similarity": 0.2722711356253558}, {"word": "ranken", "similarity": 0.2722612739863024}, {"word": "backprint", "similarity": 0.2721818962170579}, {"word": "celebrating", "similarity": 0.2721715652220395}, {"word": "pearson", "similarity": 0.27191346691726087}, {"word": "tatch", "similarity": 0.27183001339407614}, {"word": "culmination", "similarity": 0.27176351218511513}, {"word": "erose", "similarity": 0.2717566021898465}, {"word": "splot", "similarity": 0.2717220425751767}, {"word": "discrimen", "similarity": 0.27144439027531425}, {"word": "diaresis", "similarity": 0.27143667021869505}, {"word": "incontestability", "similarity": 0.27143179040279386}, {"word": "marxoid", "similarity": 0.27137266534307025}, {"word": "overbar", "similarity": 0.271362631181143}, {"word": "indications", "similarity": 0.2710671804564678}, {"word": "ineffaceable", "similarity": 0.2710350757282191}, {"word": "recelebrate", "similarity": 0.2709482161020207}, {"word": "celebratedly", "similarity": 0.2705322071125399}, {"word": "missign", "similarity": 0.2703783238868846}, {"word": "signest", "similarity": 0.2703783238868846}, {"word": "signeth", "similarity": 0.2703783238868846}, {"word": "separatrix", "similarity": 0.2703758587764955}, {"word": "foredate", "similarity": 0.2702829655167086}, {"word": "overcoding", "similarity": 0.2702398970053866}, {"word": "smutch", "similarity": 0.26995051282996013}, {"word": "picoindentation", "similarity": 0.26979966931119614}, {"word": "blemisht", "similarity": 0.269766397186571}, {"word": "apostrophes", "similarity": 0.2696776918366783}, {"word": "badged", "similarity": 0.26957747651471603}, {"word": "edges", "similarity": 0.26954310365321876}, {"word": "inustion", "similarity": 0.2695399911996093}, {"word": "untouch", "similarity": 0.26942726698823355}, {"word": "indents", "similarity": 0.2694088120128654}, {"word": "signature", "similarity": 0.26934277789196903}, {"word": "coincided", "similarity": 0.26933155499936595}, {"word": "notches", "similarity": 0.26921370001752676}, {"word": "emaculate", "similarity": 0.2689283636142705}, {"word": "logo", "similarity": 0.2689035487689124}, {"word": "score", "similarity": 0.2688928985505037}, {"word": "manicule", "similarity": 0.26884018801044474}, {"word": "remarque", "similarity": 0.2687485509503553}, {"word": "slopegraph", "similarity": 0.2687140799163795}, {"word": "misdescriptiveness", "similarity": 0.2687029370289841}, {"word": "tattooed", "similarity": 0.2686129622892583}, {"word": "presignification", "similarity": 0.26836351897873434}, {"word": "microdegree", "similarity": 0.2683576550234621}, {"word": "thirling", "similarity": 0.26824835269702846}, {"word": "consignificant", "similarity": 0.26811364405965715}, {"word": "cuspidalization", "similarity": 0.26789558999995067}, {"word": "pointest", "similarity": 0.2678005038057577}, {"word": "pointeth", "similarity": 0.2678005038057577}, {"word": "wordmark", "similarity": 0.26775777536616974}, {"word": "noted", "similarity": 0.267732478103853}, {"word": "misdescriptive", "similarity": 0.2676808703135156}, {"word": "watermarks", "similarity": 0.2676200508602803}, {"word": "sexcentenary", "similarity": 0.267442199831754}, {"word": "indentation", "similarity": 0.26716316258309825}, {"word": "demarcated", "similarity": 0.26701817670453487}, {"word": "indention", "similarity": 0.2669147186516401}, {"word": "blotching", "similarity": 0.26686249456028405}, {"word": "maculatory", "similarity": 0.26684249860856224}, {"word": "bepinch", "similarity": 0.2668150903754744}, {"word": "tattooage", "similarity": 0.2667499653816689}, {"word": "anniversarily", "similarity": 0.26648749141210504}, {"word": "brandable", "similarity": 0.266308026455126}, {"word": "marxisant", "similarity": 0.2662197540540502}, {"word": "eigensymbol", "similarity": 0.2662050777082906}, {"word": "nameplating", "similarity": 0.26620464295185253}, {"word": "noteless", "similarity": 0.266002634572029}, {"word": "logoed", "similarity": 0.26596550840734606}, {"word": "inkspot", "similarity": 0.2658974161085792}, {"word": "signet", "similarity": 0.2657405223019154}, {"word": "indent", "similarity": 0.26563425022531284}, {"word": "blemished", "similarity": 0.2654459958411354}, {"word": "chalkland", "similarity": 0.2654048384321819}, {"word": "scuffs", "similarity": 0.2652805352285168}, {"word": "inks", "similarity": 0.26520282519906974}, {"word": "scarry", "similarity": 0.26512440582955177}, {"word": "signpost", "similarity": 0.2650016995874307}, {"word": "subsymbol", "similarity": 0.26482654386210025}, {"word": "logotype", "similarity": 0.2648063521059303}, {"word": "imprintest", "similarity": 0.2647437634586799}, {"word": "imprinteth", "similarity": 0.2647437634586799}, {"word": "misimprint", "similarity": 0.2647437634586799}, {"word": "reimprint", "similarity": 0.2647437634586799}, {"word": "unindent", "similarity": 0.2646833878556004}, {"word": "microstamping", "similarity": 0.2645851374476733}, {"word": "semicharacteristic", "similarity": 0.2644098726629998}, {"word": "nonbrand", "similarity": 0.2643657787051771}, {"word": "chalks", "similarity": 0.26426070171074184}, {"word": "scarless", "similarity": 0.264112500564381}, {"word": "midpoint", "similarity": 0.26368988159227646}, {"word": "rechalk", "similarity": 0.26368469345620277}, {"word": "multibrand", "similarity": 0.2636743963773821}, {"word": "prosign", "similarity": 0.2636490774017518}, {"word": "chalk", "similarity": 0.2635087165732212}, {"word": "undistinguishing", "similarity": 0.26336018813461154}, {"word": "pertusion", "similarity": 0.26322988103667966}, {"word": "inscribed", "similarity": 0.26321737254688965}, {"word": "spot", "similarity": 0.26318589633785733}, {"word": "fortieth", "similarity": 0.2631681146258977}, {"word": "tricentenary", "similarity": 0.263114039414647}, {"word": "bechalk", "similarity": 0.2630293568135934}, {"word": "gouges", "similarity": 0.26301419469793813}, {"word": "septcentenary", "similarity": 0.26289015906770685}, {"word": "exam", "similarity": 0.26278470226580103}, {"word": "spencer", "similarity": 0.262752336386102}, {"word": "pseudolandmark", "similarity": 0.26275133301421905}, {"word": "blotchiness", "similarity": 0.26263970904799844}, {"word": "signposted", "similarity": 0.2626232637427938}, {"word": "skidmark", "similarity": 0.26259137335151084}, {"word": "stain", "similarity": 0.2625901960541227}, {"word": "corradiation", "similarity": 0.2624765750787348}, {"word": "tercentennial", "similarity": 0.2624724870153026}, {"word": "yearday", "similarity": 0.262462223422888}, {"word": "wrinkles", "similarity": 0.26234839120171866}, {"word": "classmark", "similarity": 0.2622987466450664}, {"word": "signholder", "similarity": 0.2622370667851307}, {"word": "microresidue", "similarity": 0.26217094907523303}, {"word": "punctures", "similarity": 0.26215086390703446}, {"word": "pointclass", "similarity": 0.2620893512936235}, {"word": "presignature", "similarity": 0.2620585286404678}, {"word": "significatory", "similarity": 0.26201682466150705}, {"word": "twentiethly", "similarity": 0.261982129748578}, {"word": "sixt", "similarity": 0.2619723729000855}, {"word": "chalklike", "similarity": 0.2619242450052655}, {"word": "ligature", "similarity": 0.26189226143899313}, {"word": "demarcate", "similarity": 0.26182479705801154}, {"word": "prelabeled", "similarity": 0.2617782048865154}, {"word": "pustulate", "similarity": 0.2617765011909114}, {"word": "signifiers", "similarity": 0.2615454469802118}, {"word": "unconspicuous", "similarity": 0.26153026720934414}, {"word": "signee", "similarity": 0.2615106396578129}, {"word": "zuckerberg", "similarity": 0.26144603977829}, {"word": "ink", "similarity": 0.2614248038512801}, {"word": "furrows", "similarity": 0.2613984966153163}, {"word": "seventieth", "similarity": 0.2613894213456795}, {"word": "bechalked", "similarity": 0.2613711180101736}, {"word": "blemishable", "similarity": 0.2612272800781657}, {"word": "blemisher", "similarity": 0.2612272800781657}, {"word": "smutches", "similarity": 0.26115190622325796}, {"word": "percentile", "similarity": 0.26096879738746975}, {"word": "guillemet", "similarity": 0.2609099222918472}, {"word": "identifying", "similarity": 0.26076440443814486}, {"word": "commas", "similarity": 0.2605781231250392}, {"word": "debrand", "similarity": 0.26052374137299966}, {"word": "demarcationalism", "similarity": 0.26050840944393333}, {"word": "overink", "similarity": 0.2602329706910719}, {"word": "indicable", "similarity": 0.2600475284374287}, {"word": "coincide", "similarity": 0.2598339369603822}, {"word": "marke", "similarity": 0.259816271748495}, {"word": "betoken", "similarity": 0.2597155317602494}, {"word": "bicuspidal", "similarity": 0.2596830400684956}, {"word": "badgemaking", "similarity": 0.2596512356784745}, {"word": "scrawled", "similarity": 0.2596322297225993}, {"word": "watermark", "similarity": 0.25956728675597607}, {"word": "impressure", "similarity": 0.25956365567710304}, {"word": "tarnishment", "similarity": 0.25949370769929925}, {"word": "comma", "similarity": 0.2594008828494243}, {"word": "distinguishingly", "similarity": 0.2593561586932141}, {"word": "taggant", "similarity": 0.2592867904708575}, {"word": "notator", "similarity": 0.2592462247938522}, {"word": "handstamp", "similarity": 0.259212625082588}, {"word": "celebrious", "similarity": 0.25918822625650456}, {"word": "cicatrise", "similarity": 0.2591683727103231}, {"word": "demarcator", "similarity": 0.25912906876663255}, {"word": "smudgeproof", "similarity": 0.2591122483900471}, {"word": "signifer", "similarity": 0.25908886115428315}, {"word": "oversignify", "similarity": 0.2590862054179963}, {"word": "pointset", "similarity": 0.2589738611629547}, {"word": "engrail", "similarity": 0.2589643175521251}, {"word": "prelabelled", "similarity": 0.25874895486243127}, {"word": "quadricuspid", "similarity": 0.25838364939945563}, {"word": "ligatured", "similarity": 0.25837571888752425}, {"word": "spitzer", "similarity": 0.2583553847588167}, {"word": "diacritics", "similarity": 0.25820400041554004}, {"word": "cusp", "similarity": 0.2581473800461282}, {"word": "immunodot", "similarity": 0.2581347970281703}, {"word": "unstarred", "similarity": 0.2580075957180316}, {"word": "identifiable", "similarity": 0.2579981310668666}, {"word": "signalizing", "similarity": 0.2579613777864866}, {"word": "percentiler", "similarity": 0.2578929469500684}, {"word": "lineation", "similarity": 0.2578199396708082}, {"word": "kenspeckle", "similarity": 0.25779868413934665}, {"word": "unnoting", "similarity": 0.25771373515393986}, {"word": "nonpoints", "similarity": 0.25756735220877847}, {"word": "mottles", "similarity": 0.25752822047362645}, {"word": "marcato", "similarity": 0.257357586040013}, {"word": "freckling", "similarity": 0.25721594975072287}, {"word": "predesignation", "similarity": 0.25718838863697835}, {"word": "striate", "similarity": 0.25704821750430074}, {"word": "tattoos", "similarity": 0.2569957996568171}, {"word": "undernoted", "similarity": 0.2568996570759327}, {"word": "scuffed", "similarity": 0.2568141053059068}, {"word": "pfenig", "similarity": 0.25679640811525134}, {"word": "denotation", "similarity": 0.2565777268693637}, {"word": "splodge", "similarity": 0.25656566646561996}, {"word": "stippled", "similarity": 0.25655456101221025}, {"word": "cuspal", "similarity": 0.25654490358745113}, {"word": "welts", "similarity": 0.2563618412715354}, {"word": "underlined", "similarity": 0.25630545546634065}, {"word": "noticeableness", "similarity": 0.25629744064184967}, {"word": "striation", "similarity": 0.2560506080715624}, {"word": "nonindicated", "similarity": 0.2559387950457446}, {"word": "hickeys", "similarity": 0.25577485744458606}, {"word": "deciare", "similarity": 0.25575112609622447}, {"word": "scuff", "similarity": 0.25574440280512006}, {"word": "dvojnice", "similarity": 0.2557118561329415}, {"word": "pointee", "similarity": 0.2556249677480944}, {"word": "cicatricial", "similarity": 0.2555510244754076}, {"word": "martin", "similarity": 0.25541132953286544}, {"word": "tattooing", "similarity": 0.25539775407550147}, {"word": "bewrinkled", "similarity": 0.25533123073163927}, {"word": "counterdistinction", "similarity": 0.25513510660528826}, {"word": "residue", "similarity": 0.2551272246418038}, {"word": "cairned", "similarity": 0.25479665534426926}, {"word": "characteristical", "similarity": 0.2547279012858625}, {"word": "apostrophe", "similarity": 0.2547198572206321}, {"word": "smudgily", "similarity": 0.2546918821469548}, {"word": "smudginess", "similarity": 0.2546918821469548}, {"word": "prosilient", "similarity": 0.2546494849145817}, {"word": "underprint", "similarity": 0.25457055377683996}, {"word": "ticked", "similarity": 0.25456909557388374}, {"word": "stipple", "similarity": 0.25432017561114784}, {"word": "antiscuff", "similarity": 0.2540111856861447}, {"word": "nonscuff", "similarity": 0.2540111856861447}, {"word": "noticeability", "similarity": 0.25378700659123804}, {"word": "premices", "similarity": 0.2537641928379094}, {"word": "examsmanship", "similarity": 0.2536489711327234}, {"word": "mcburney", "similarity": 0.2535827531813149}, {"word": "discolouration", "similarity": 0.25350428646729595}, {"word": "mathew", "similarity": 0.2534975227607336}, {"word": "commemoratory", "similarity": 0.2532749298662688}, {"word": "registered", "similarity": 0.2531235151236099}, {"word": "fistnote", "similarity": 0.2531129075166722}, {"word": "foresignification", "similarity": 0.25302377609272886}, {"word": "dioristic", "similarity": 0.2530062158087889}, {"word": "indicated", "similarity": 0.2529540582078694}, {"word": "reink", "similarity": 0.2528798755703678}, {"word": "notate", "similarity": 0.2528794197292962}, {"word": "firstness", "similarity": 0.2528648626536727}, {"word": "reinking", "similarity": 0.252768160341332}, {"word": "unsign", "similarity": 0.25267731361251156}, {"word": "brandification", "similarity": 0.25265161028805383}, {"word": "quincentennium", "similarity": 0.25264410506188956}, {"word": "intervisible", "similarity": 0.25258153856504784}, {"word": "labeled", "similarity": 0.2524601178723662}, {"word": "puncture", "similarity": 0.2524190444712129}, {"word": "decemdentate", "similarity": 0.2524085558650867}, {"word": "cusped", "similarity": 0.2521693525265659}, {"word": "designation", "similarity": 0.2520898861120691}, {"word": "tags", "similarity": 0.2520835568193346}, {"word": "highspot", "similarity": 0.252051671125484}, {"word": "1st", "similarity": 0.25201672469910974}, {"word": "letts", "similarity": 0.25189429352457643}, {"word": "distinguishment", "similarity": 0.25174928492902937}, {"word": "cicatrize", "similarity": 0.25169691945976375}, {"word": "notching", "similarity": 0.25169505189552993}, {"word": "stichometry", "similarity": 0.2514076217502899}, {"word": "sesquicentennial", "similarity": 0.25138231930394056}, {"word": "dents", "similarity": 0.2513221735647454}, {"word": "intercuspidal", "similarity": 0.25122136873446954}, {"word": "engrailment", "similarity": 0.2510863545341766}, {"word": "indicator", "similarity": 0.2510846364138406}, {"word": "scratches", "similarity": 0.25108016142362116}, {"word": "daymark", "similarity": 0.25097399586973995}, {"word": "scrawls", "similarity": 0.25087478902951876}, {"word": "rebranding", "similarity": 0.25076354268871676}, {"word": "trichion", "similarity": 0.2507199976202404}, {"word": "tompkins", "similarity": 0.25053650170505043}, {"word": "intrenchant", "similarity": 0.25052292929411674}, {"word": "residueless", "similarity": 0.2505073249903041}, {"word": "bipunctual", "similarity": 0.2504860079899606}, {"word": "germain", "similarity": 0.25042334237443303}, {"word": "scores", "similarity": 0.25028783627886886}, {"word": "bewrinkle", "similarity": 0.2502330797313926}, {"word": "unicuspidal", "similarity": 0.25018857625146246}, {"word": "stainest", "similarity": 0.2501305470657475}, {"word": "staineth", "similarity": 0.2501305470657475}, {"word": "veganniversary", "similarity": 0.2500271047107224}, {"word": "strikethrough", "similarity": 0.24996113377989013}, {"word": "histoscore", "similarity": 0.24981864683993513}, {"word": "antroscopy", "similarity": 0.24971663111757697}, {"word": "commata", "similarity": 0.24958402929045803}, {"word": "noticable", "similarity": 0.24936202479128017}, {"word": "centennial", "similarity": 0.24929298156784574}, {"word": "dilabeled", "similarity": 0.24925382350449865}, {"word": "monolabeled", "similarity": 0.24925382350449865}, {"word": "beblot", "similarity": 0.24914320358800512}, {"word": "chaulk", "similarity": 0.24909507503886408}, {"word": "subpoint", "similarity": 0.24905221851040338}, {"word": "notaulix", "similarity": 0.24883193713409868}, {"word": "brandalism", "similarity": 0.24881868485152397}, {"word": "predesignate", "similarity": 0.24881387860313228}, {"word": "yeartide", "similarity": 0.2487385896247925}, {"word": "deathday", "similarity": 0.24872958208181534}, {"word": "punction", "similarity": 0.24872066237607046}, {"word": "mensiversary", "similarity": 0.24871667329999464}, {"word": "indice", "similarity": 0.2485185569535749}, {"word": "midlick", "similarity": 0.24843319290848911}, {"word": "commencement", "similarity": 0.2483813537063697}, {"word": "juneteenth", "similarity": 0.2482928182783717}, {"word": "geresh", "similarity": 0.2481818741939609}, {"word": "microstriation", "similarity": 0.24817836076115735}, {"word": "plooky", "similarity": 0.24815250821048238}, {"word": "signator", "similarity": 0.2481488997919338}, {"word": "crosspoint", "similarity": 0.24788666487553954}, {"word": "##st", "similarity": 0.2478331514082929}, {"word": "splodgy", "similarity": 0.24766828363981794}, {"word": "sesquicentenarian", "similarity": 0.247659448558202}, {"word": "scarification", "similarity": 0.24756654919129187}, {"word": "yahrzeit", "similarity": 0.24750068110324158}, {"word": "tetracuspid", "similarity": 0.24745866978525874}, {"word": "discoloration", "similarity": 0.24736616955306062}, {"word": "semialgebra", "similarity": 0.247349751964766}, {"word": "furrower", "similarity": 0.24726130329064336}, {"word": "characterism", "similarity": 0.24723232708031348}, {"word": "birthdayless", "similarity": 0.2471128352725101}, {"word": "brander", "similarity": 0.24710782048286248}, {"word": "seamark", "similarity": 0.2470866027236603}, {"word": "cadency", "similarity": 0.24699653199822483}, {"word": "notest", "similarity": 0.2469743913977889}, {"word": "postmark", "similarity": 0.2469104613290815}, {"word": "matthew", "similarity": 0.24682016742476423}, {"word": "aculeolate", "similarity": 0.24675958868257467}, {"word": "squiggles", "similarity": 0.24674586930794554}, {"word": "definatory", "similarity": 0.2467392590843432}, {"word": "tick", "similarity": 0.24672696019802656}, {"word": "labelling", "similarity": 0.2467149909247543}, {"word": "orthoradial", "similarity": 0.2467033056915045}, {"word": "footmarks", "similarity": 0.24651877501737235}, {"word": "subsignature", "similarity": 0.24643819700066238}, {"word": "cusper", "similarity": 0.24638958366209862}, {"word": "unstamped", "similarity": 0.24635828264419307}, {"word": "rebirthday", "similarity": 0.24631851224258916}, {"word": "cuspate", "similarity": 0.24630374470018174}, {"word": "distinguishness", "similarity": 0.2461743422248508}, {"word": "stamps", "similarity": 0.2461418776459673}, {"word": "morphoeic", "similarity": 0.2460181652926506}, {"word": "midterm", "similarity": 0.245977110956605}, {"word": "prathama", "similarity": 0.24593610492016485}, {"word": "brandscaping", "similarity": 0.2458921866531042}, {"word": "ulerythema", "similarity": 0.24586648622813492}, {"word": "highlighter", "similarity": 0.2457469983203623}, {"word": "skintag", "similarity": 0.2457103851500575}, {"word": "puncturation", "similarity": 0.24570147281555405}, {"word": "anniversal", "similarity": 0.2456375099523226}, {"word": "postsymbolic", "similarity": 0.2455004629589876}, {"word": "smearable", "similarity": 0.2454186279471931}, {"word": "spotty", "similarity": 0.24534221429145095}, {"word": "blot", "similarity": 0.24527565796949716}, {"word": "forehead", "similarity": 0.24526240086297432}, {"word": "metalmark", "similarity": 0.2452176453977396}, {"word": "incise", "similarity": 0.2450779290490723}, {"word": "indicators", "similarity": 0.24504850889759955}, {"word": "copoint", "similarity": 0.24501890229919024}, {"word": "biphenotypy", "similarity": 0.2450153055301628}, {"word": "swastika", "similarity": 0.24498472093953508}, {"word": "noting", "similarity": 0.24491662067425582}, {"word": "cusplet", "similarity": 0.24486354154585185}, {"word": "cuspule", "similarity": 0.24486354154585185}, {"word": "fim", "similarity": 0.2447844708075233}, {"word": "subsymbolic", "similarity": 0.24476549820035284}, {"word": "inklike", "similarity": 0.24468981863395958}, {"word": "demarcational", "similarity": 0.24465629945412704}, {"word": "indentedness", "similarity": 0.24465151250098188}, {"word": "noteth", "similarity": 0.24448971795156524}, {"word": "chanelism", "similarity": 0.24445446812717014}, {"word": "postmarks", "similarity": 0.24430902846475122}, {"word": "puncticular", "similarity": 0.24428849967384397}, {"word": "splotch", "similarity": 0.24426748719006178}, {"word": "tenths", "similarity": 0.24418306151399366}, {"word": "fifteenth", "similarity": 0.24416681710144303}, {"word": "penciling", "similarity": 0.2440848204132342}, {"word": "singled", "similarity": 0.24406739546397702}, {"word": "birthday", "similarity": 0.24394890627975616}, {"word": "sublineation", "similarity": 0.2439149721424643}, {"word": "prostriate", "similarity": 0.24386092104839588}, {"word": "preexamination", "similarity": 0.24384563187392794}, {"word": "footprints", "similarity": 0.24379854106262142}, {"word": "antimeridian", "similarity": 0.24367617556208668}, {"word": "predates", "similarity": 0.24359447659079064}, {"word": "macy", "similarity": 0.24336991429003144}, {"word": "hoarstone", "similarity": 0.2432040846124182}, {"word": "impressions", "similarity": 0.2432004860491621}, {"word": "anniverse", "similarity": 0.24299866546708138}, {"word": "footprinted", "similarity": 0.242698945015073}, {"word": "demarcation", "similarity": 0.2425321604499668}, {"word": "5th", "similarity": 0.24250739853091272}, {"word": "exams", "similarity": 0.24237274939980874}, {"word": "chalkable", "similarity": 0.2423453829082822}, {"word": "tidemark", "similarity": 0.24231991075243675}, {"word": "scorepad", "similarity": 0.24228775268140137}, {"word": "pointedness", "similarity": 0.24220221208542034}, {"word": "seth", "similarity": 0.24212976938956796}, {"word": "8th", "similarity": 0.24199361147766155}, {"word": "coincider", "similarity": 0.24196498363538754}, {"word": "antroscopic", "similarity": 0.2419299674496632}, {"word": "blotty", "similarity": 0.24179736942836322}, {"word": "fylfot", "similarity": 0.24175201497206852}, {"word": "subgross", "similarity": 0.24174468276887526}, {"word": "underscores", "similarity": 0.24162966658415888}, {"word": "noncelebration", "similarity": 0.2416034187738563}, {"word": "cooccur", "similarity": 0.24158486451675926}, {"word": "backtag", "similarity": 0.24157055624554205}, {"word": "unmistakable", "similarity": 0.2414248881928875}, {"word": "interstria", "similarity": 0.24135831948613365}, {"word": "striature", "similarity": 0.24135831948613365}, {"word": "virgula", "similarity": 0.24135025900096901}, {"word": "sealwax", "similarity": 0.2413484756974999}, {"word": "tag", "similarity": 0.2413248462641074}, {"word": "stainings", "similarity": 0.24129953075605018}, {"word": "puncturer", "similarity": 0.24129198223286297}, {"word": "puncturable", "similarity": 0.2410843920337717}, {"word": "overstain", "similarity": 0.24106834842956204}, {"word": "gnaborretni", "similarity": 0.24097352354513005}, {"word": "indenting", "similarity": 0.24096318387984197}, {"word": "distinguishes", "similarity": 0.24093003606467003}, {"word": "inscriptionless", "similarity": 0.24091748751623748}, {"word": "cobrand", "similarity": 0.24079271110520242}, {"word": "obelus", "similarity": 0.24069446298324304}, {"word": "noughth", "similarity": 0.24052959485582556}, {"word": "penciled", "similarity": 0.24051638830853622}, {"word": "firsts", "similarity": 0.24042206993032536}, {"word": "highlighting", "similarity": 0.2403719079440564}, {"word": "watermarked", "similarity": 0.24030486421048383}, {"word": "unbranded", "similarity": 0.2402270387088535}, {"word": "costained", "similarity": 0.24018159657303198}, {"word": "stainproof", "similarity": 0.24015270622330126}, {"word": "multicuspid", "similarity": 0.24009902233662375}, {"word": "imprinted", "similarity": 0.24009303983179892}, {"word": "interrobang", "similarity": 0.23995721095633243}, {"word": "historied", "similarity": 0.2398312978339123}, {"word": "wemless", "similarity": 0.2398302986867749}, {"word": "multisign", "similarity": 0.2398027149261064}, {"word": "tattooee", "similarity": 0.23973774442068982}, {"word": "plashy", "similarity": 0.23971224748181205}, {"word": "blemishless", "similarity": 0.23969894520850374}, {"word": "bidirected", "similarity": 0.2394387129006273}, {"word": "fifteenthly", "similarity": 0.23941612626270667}, {"word": "rotulus", "similarity": 0.23938200222241682}, {"word": "stippling", "similarity": 0.23937299737783482}, {"word": "pencilliform", "similarity": 0.23910108159911642}, {"word": "coindication", "similarity": 0.23908604789042562}, {"word": "dedent", "similarity": 0.23905399715618583}, {"word": "notable", "similarity": 0.2390009914936804}, {"word": "annish", "similarity": 0.2389794236230356}, {"word": "unaiming", "similarity": 0.23895516187678184}, {"word": "scrawl", "similarity": 0.2388996738093568}, {"word": "recelebration", "similarity": 0.23889965964096463}, {"word": "notandum", "similarity": 0.23887821490424238}, {"word": "rasion", "similarity": 0.23878268626775262}, {"word": "recognisable", "similarity": 0.23876651765709517}, {"word": "twelfth", "similarity": 0.23863974619894815}, {"word": "signposting", "similarity": 0.23840212380493292}, {"word": "pfenning", "similarity": 0.23838131959630066}, {"word": "interlabel", "similarity": 0.23829090418387905}, {"word": "ostruble", "similarity": 0.2382498284374384}, {"word": "smudging", "similarity": 0.2381553625221168}, {"word": "indicative", "similarity": 0.2380552392654239}, {"word": "birthdayish", "similarity": 0.23796652480742533}, {"word": "centile", "similarity": 0.23795911782739598}, {"word": "presignify", "similarity": 0.23784149237720584}, {"word": "stickers", "similarity": 0.2378135621651079}, {"word": "misbrand", "similarity": 0.23779614746970942}, {"word": "signaled", "similarity": 0.2377885324415432}, {"word": "tracest", "similarity": 0.2377271915582151}, {"word": "traceth", "similarity": 0.2377271915582151}, {"word": "milligrade", "similarity": 0.2376721218437423}, {"word": "jubilee", "similarity": 0.23766085192843478}, {"word": "buist", "similarity": 0.2375328040050445}, {"word": "macropuncture", "similarity": 0.2374842287695903}, {"word": "pencilled", "similarity": 0.23748007953048025}, {"word": "unmistakableness", "similarity": 0.23746729795867497}, {"word": "apostrophectomy", "similarity": 0.237421783203339}, {"word": "recognizable", "similarity": 0.23734909810603966}, {"word": "scoring", "similarity": 0.23733558718319153}, {"word": "anagraphy", "similarity": 0.23729808892325804}, {"word": "morphew", "similarity": 0.23728983984010035}, {"word": "prestamp", "similarity": 0.23717884825715715}, {"word": "noteworthy", "similarity": 0.23717269804593605}, {"word": "newman", "similarity": 0.2371501517652883}, {"word": "marred", "similarity": 0.23714163187013274}, {"word": "immarginate", "similarity": 0.23708940460254455}, {"word": "hundredth", "similarity": 0.23707285528498384}, {"word": "isocryme", "similarity": 0.23687364385452628}, {"word": "gammadion", "similarity": 0.23680178369383595}, {"word": "dayboard", "similarity": 0.2367831002557766}, {"word": "intercuspation", "similarity": 0.23672741024666058}, {"word": "radiomarked", "similarity": 0.23669098156717994}, {"word": "thirtieth", "similarity": 0.23664473944349057}, {"word": "serrulation", "similarity": 0.23663775502617146}, {"word": "birthdate", "similarity": 0.2365821797551051}, {"word": "significator", "similarity": 0.2365686173965371}, {"word": "tricentennial", "similarity": 0.23621690430237433}, {"word": "stripes", "similarity": 0.2362160560225912}, {"word": "note", "similarity": 0.23618807132984546}, {"word": "speckles", "similarity": 0.23617277966682582}, {"word": "equicharacteristic", "similarity": 0.2360966469428107}, {"word": "natalitial", "similarity": 0.23605097294378632}, {"word": "tetraskelion", "similarity": 0.2360266459373686}, {"word": "emblems", "similarity": 0.2360046053744338}, {"word": "drypoint", "similarity": 0.2359788106101783}, {"word": "orthodiagraphic", "similarity": 0.23597470014589603}, {"word": "beginning", "similarity": 0.23584194193130767}, {"word": "unnotched", "similarity": 0.2358200452709289}, {"word": "triarian", "similarity": 0.23580020718533018}, {"word": "demarkation", "similarity": 0.23575267376481907}, {"word": "isovist", "similarity": 0.23566992141574228}, {"word": "emblem", "similarity": 0.23556004815870404}, {"word": "centesimal", "similarity": 0.2355384720096}]